setup.cfg
setup.py
pyschema/__init__.py
pyschema/core.py
pyschema/source_generation.py
pyschema/types.py
pyschema.egg-info/PKG-INFO
pyschema.egg-info/SOURCES.txt
pyschema.egg-info/dependency_links.txt
pyschema.egg-info/namespace_packages.txt
pyschema.egg-info/pbr.json
pyschema.egg-info/requires.txt
pyschema.egg-info/top_level.txt
pyschema/contrib/__init__.py
pyschema/contrib/avro.py
pyschema/contrib/avro_to_pyschema.py
pyschema/contrib/jsonschema.py
pyschema/contrib/luigi.py
pyschema/contrib/postgres.py
pyschema_extensions/__init__.py
pyschema_extensions/avro.py
pyschema_extensions/avro_schema_parser.py
pyschema_extensions/avro_to_pyschema.py
pyschema_extensions/jsonschema.py
pyschema_extensions/luigi.py
pyschema_extensions/postgres.py
test/tests.py