Metadata-Version: 1.0
Name: pyschema
Version: 2.4.0
Summary: Schema definition and serialisation library
Home-page: http://github.com/spotify/pyschema
Author: Elias Freider
Author-email: freider@spotify.com
License: UNKNOWN
Keywords: schema,avro,postgres,json
Platform: UNKNOWN
